rainaa/aunly/t2i/__init__.py
rainaa/aunly/t2i/strings.py
RainAa_Utils_AunlyT2i-0.0.1.dist-info/METADATA
RainAa_Utils_AunlyT2i-0.0.1.dist-info/WHEEL
RainAa_Utils_AunlyT2i-0.0.1.dist-info/top_level.txt
RainAa_Utils_AunlyT2i-0.0.1.dist-info/RECORD
