Metadata-Version: 2.1
Name: RainAa-Utils-AunlyT2i
Version: 0.0.1
Author-email: Little-LinNian <2544704967@qq.com>
License: MIT
Requires-Python: >=3.9
Requires-Dist: Pillow (>=9.5.0)
Requires-Dist: graiax-text2img-playwright (>=0.4.0)
Requires-Dist: minidynamicrender (>=1.1.9)
Requires-Dist: rainaa-res-fonts (>=0.0.1)
Requires-Dist: brotli (>=1.0.9)
